data_transformation_library/__init__.py
data_transformation_library/cross_correlation.py
data_transformation_library/time_series_windowing.py
data_transformation_library/transpose.py
data_transformation_library_jmarci-0.1.12.dist-info/METADATA
data_transformation_library_jmarci-0.1.12.dist-info/WHEEL
data_transformation_library_jmarci-0.1.12.dist-info/RECORD
